{
  "title": "Phê duyệt thanh toán",
  "category": "Tài chính",
  "description": "Quy trình phê duyệt thanh toán cho nhà cung cấp",
  "icon": "credit-card",
  "steps": [
    {
      "step_id": "start",
      "step_type": "Start",
      "label": "Bắt đầu",
      "step_order": 1
    },
    {
      "step_id": "prepare",
      "step_type": "Task",
      "label": "Kế toán lập ủy nhiệm chi",
      "step_order": 2,
      "executor_type": "Role",
      "executor_value": "Accounts Manager",
      "form_schema": "[{\"key\": \"so_tien\", \"label\": \"Số tiền thanh toán (VNĐ)\", \"type\": \"number\", \"required\": true}, {\"key\": \"noi_dung\", \"label\": \"Nội dung thanh toán\", \"type\": \"textarea\", \"required\": true}, {\"key\": \"phuong_thuc\", \"label\": \"Phương thức thanh toán\", \"type\": \"select\", \"required\": true, \"options\": [\"Chuyển khoản\", \"Tiền mặt\", \"Séc\"]}, {\"key\": \"tai_khoan_thu_huong\", \"label\": \"Tài khoản thụ hưởng\", \"type\": \"text\", \"required\": true}, {\"key\": \"ten_thu_huong\", \"label\": \"Tên người thụ hưởng\", \"type\": \"text\", \"required\": true}, {\"key\": \"ngan_hang\", \"label\": \"Ngân hàng thụ hưởng\", \"type\": \"text\", \"required\": true}, {\"key\": \"ngay_thanh_toan\", \"label\": \"Ngày thanh toán dự kiến\", \"type\": \"date\", \"required\": true}, {\"key\": \"so_hoa_don\", \"label\": \"Số hóa đơn liên quan\", \"type\": \"text\", \"required\": false}]"
    },
    {
      "step_id": "approve",
      "step_type": "Approval",
      "label": "Giám đốc ký duyệt",
      "step_order": 3,
      "executor_type": "Role",
      "executor_value": "System Manager",
      "no_return": 1
    },
    {
      "step_id": "bank_transfer",
      "step_type": "Task",
      "label": "Thực hiện chuyển khoản",
      "step_order": 4,
      "executor_type": "Role",
      "executor_value": "Accounts Manager",
      "form_schema": "[{\"key\": \"ma_giao_dich\", \"label\": \"Mã giao dịch ngân hàng\", \"type\": \"text\", \"required\": true}, {\"key\": \"ngay_thuc_hien\", \"label\": \"Ngày thực hiện\", \"type\": \"date\", \"required\": true}, {\"key\": \"ghi_chu\", \"label\": \"Ghi chú\", \"type\": \"textarea\", \"required\": false}]"
    },
    {
      "step_id": "end",
      "step_type": "End",
      "label": "Kết thúc",
      "step_order": 5
    }
  ],
  "transitions": [
    {
      "from_step": "start",
      "to_step": "prepare",
      "action_trigger": "Send",
      "condition_type": "Always"
    },
    {
      "from_step": "prepare",
      "to_step": "approve",
      "action_trigger": "Send",
      "condition_type": "Always"
    },
    {
      "from_step": "approve",
      "to_step": "bank_transfer",
      "action_trigger": "Approve",
      "condition_type": "Always"
    },
    {
      "from_step": "approve",
      "to_step": "prepare",
      "action_trigger": "Reject",
      "condition_type": "Always"
    },
    {
      "from_step": "bank_transfer",
      "to_step": "end",
      "action_trigger": "Send",
      "condition_type": "Always"
    }
  ]
}
